{
	"cmake" : 
	{
		"generator" : 
		{
			"multiConfig" : false,
			"name" : "MinGW Makefiles"
		},
		"paths" : 
		{
			"cmake" : "C:/Users/Admin/AppData/Local/JetBrains/CLion 2023.1.2/bin/cmake/win/x64/bin/cmake.exe",
			"cpack" : "C:/Users/Admin/AppData/Local/JetBrains/CLion 2023.1.2/bin/cmake/win/x64/bin/cpack.exe",
			"ctest" : "C:/Users/Admin/AppData/Local/JetBrains/CLion 2023.1.2/bin/cmake/win/x64/bin/ctest.exe",
			"root" : "C:/Users/Admin/AppData/Local/JetBrains/CLion 2023.1.2/bin/cmake/win/x64/share/cmake-3.25"
		},
		"version" : 
		{
			"isDirty" : false,
			"major" : 3,
			"minor" : 25,
			"patch" : 2,
			"string" : "3.25.2",
			"suffix" : ""
		}
	},
	"objects" : 
	[
		{
			"jsonFile" : "codemodel-v2-7fa3c1a1fc2ec0a5d919.json",
			"kind" : "codemodel",
			"version" : 
			{
				"major" : 2,
				"minor" : 4
			}
		},
		{
			"jsonFile" : "cache-v2-f75d1c0292250e23de2a.json",
			"kind" : "cache",
			"version" : 
			{
				"major" : 2,
				"minor" : 0
			}
		},
		{
			"jsonFile" : "cmakeFiles-v1-712e7ad4afd58f559550.json",
			"kind" : "cmakeFiles",
			"version" : 
			{
				"major" : 1,
				"minor" : 0
			}
		},
		{
			"jsonFile" : "toolchains-v1-1b7616c54c7e0938797c.json",
			"kind" : "toolchains",
			"version" : 
			{
				"major" : 1,
				"minor" : 0
			}
		}
	],
	"reply" : 
	{
		"cache-v2" : 
		{
			"jsonFile" : "cache-v2-f75d1c0292250e23de2a.json",
			"kind" : "cache",
			"version" : 
			{
				"major" : 2,
				"minor" : 0
			}
		},
		"cmakeFiles-v1" : 
		{
			"jsonFile" : "cmakeFiles-v1-712e7ad4afd58f559550.json",
			"kind" : "cmakeFiles",
			"version" : 
			{
				"major" : 1,
				"minor" : 0
			}
		},
		"codemodel-v2" : 
		{
			"jsonFile" : "codemodel-v2-7fa3c1a1fc2ec0a5d919.json",
			"kind" : "codemodel",
			"version" : 
			{
				"major" : 2,
				"minor" : 4
			}
		},
		"toolchains-v1" : 
		{
			"jsonFile" : "toolchains-v1-1b7616c54c7e0938797c.json",
			"kind" : "toolchains",
			"version" : 
			{
				"major" : 1,
				"minor" : 0
			}
		}
	}
}
